convmag/__init__.py
convmag/cli.py
convmag/convmag_functions.py
convmag-0.1.2.dist-info/licenses/LICENSE
convmag-0.1.2.dist-info/METADATA
convmag-0.1.2.dist-info/WHEEL
convmag-0.1.2.dist-info/entry_points.txt
convmag-0.1.2.dist-info/top_level.txt
convmag-0.1.2.dist-info/RECORD
