Metadata-Version: 2.4
Name: convmag
Version: 0.1.2
Summary: Conversion between units used in magnetism.
Author: Thomas G. Woodcock, The convmag Developers
License-Expression: MIT
Project-URL: Source, https://github.com/tgwoodcock/convmag.git
Project-URL: Bug Tracker, https://github.com/tgwoodcock/convmag.git/issues
Keywords: python,conversion,units,magnetism,magnetic
Classifier: Programming Language :: Python :: 3
Classifier: Development Status :: 4 - Beta
Classifier: Intended Audience :: End Users/Desktop
Classifier: Intended Audience :: Science/Research
Classifier: Operating System :: OS Independent
Classifier: Topic :: Scientific/Engineering
Classifier: Topic :: Scientific/Engineering :: Physics
Classifier: Topic :: Utilities
Requires-Python: >=3.6
License-File: LICENSE
Provides-Extra: dev
Requires-Dist: ruff; extra == "dev"
Requires-Dist: pre-commit>=1.16; extra == "dev"
Dynamic: license-file
